macdesigner/__init__.py
macdesigner/ayme_test.ipynb
macdesigner/cli.py
macdesigner/macdesigner.py
macdesigner/svg/b_harmonics.svg
macdesigner/svg/plane_x_b.svg
macdesigner-0.1.1.dist-info/LICENSE
macdesigner-0.1.1.dist-info/WHEEL
macdesigner-0.1.1.dist-info/METADATA
macdesigner-0.1.1.dist-info/RECORD
