Metadata-Version: 2.1
Name: macdesigner
Version: 0.1.1
Summary: Top-level package for macdesigner.
Author-email: DICORCA <jmmauricio6@gmail.com>
Classifier: License :: OSI Approved :: MIT License
